pin_passcode/__init__.py
pin_passcode/middleware.py
pin_passcode/models.py
pin_passcode/tests.py
pin_passcode/urls.py
pin_passcode/views.py
pin_passcode/static/js/jquery.js
pin_passcode/templates/pin_passcode/form.html
django_pin_passcode-0.3.1.dist-info/LICENSE.md
django_pin_passcode-0.3.1.dist-info/METADATA
django_pin_passcode-0.3.1.dist-info/WHEEL
django_pin_passcode-0.3.1.dist-info/top_level.txt
django_pin_passcode-0.3.1.dist-info/RECORD
