Metadata-Version: 2.1
Name: django-pin-passcode
Version: 0.3.1
Summary: A simple django app that provides site-wide easy password authentication for 1 user
Home-page: https://github.com/ckcollab/django-pin-passcode
Author: Eric Carmichael
Author-email: eric@ckcollab.com
License: MIT
Platform: UNKNOWN
Classifier: Intended Audience :: Developers
Classifier: Natural Language :: English
Classifier: License :: OSI Approved :: MIT License
Classifier: Operating System :: OS Independent
Classifier: Programming Language :: Python
Classifier: Programming Language :: Python :: 2
Classifier: Programming Language :: Python :: 2.6
Classifier: Programming Language :: Python :: 2.7
Classifier: Programming Language :: Python :: 3.5
Classifier: Topic :: Software Development :: Libraries :: Python Modules
